opengeode_geosciencesio/__init__.py
opengeode_geosciencesio/__init__.pyi
opengeode_geosciencesio/mesh_geosciencesio.py
opengeode_geosciencesio/mesh_geosciencesio.pyi
opengeode_geosciencesio/model_geosciencesio.py
opengeode_geosciencesio/model_geosciencesio.pyi
opengeode_geosciencesio/py.typed
opengeode_geosciencesio/bin/OpenGeode-GeosciencesIO_mesh.dll
opengeode_geosciencesio/bin/OpenGeode-GeosciencesIO_model.dll
opengeode_geosciencesio/bin/__init__.pyi
opengeode_geosciencesio/bin/opengeode_geosciencesio_py_mesh.cp310-win_amd64.pyd
opengeode_geosciencesio/bin/opengeode_geosciencesio_py_mesh.pyi
opengeode_geosciencesio/bin/opengeode_geosciencesio_py_model.cp310-win_amd64.pyd
opengeode_geosciencesio/bin/opengeode_geosciencesio_py_model.pyi
opengeode_geosciencesio-5.8.7.dist-info/METADATA
opengeode_geosciencesio-5.8.7.dist-info/WHEEL
opengeode_geosciencesio-5.8.7.dist-info/top_level.txt
opengeode_geosciencesio-5.8.7.dist-info/RECORD
