Metadata-Version: 2.4
Name: OpenGeode-GeosciencesIO
Version: 5.8.7
Summary: Input/Output formats for OpenGeode-Geosciences
Author-email: Geode-solutions <contact@geode-solutions.com>
License: MIT
Requires-Python: <3.13,>=3.9
Requires-Dist: opengeode-core==15.*,>=15.30.9
Requires-Dist: opengeode-geosciences==9.*,>=9.5.5
Requires-Dist: opengeode-io==7.*,>=7.4.6
